aiobfd/__init__.py
aiobfd/__main__.py
aiobfd/control.py
aiobfd/packet.py
aiobfd/session.py
aiobfd/transport.py
aiobfd-0.2.dist-info/DESCRIPTION.rst
aiobfd-0.2.dist-info/METADATA
aiobfd-0.2.dist-info/RECORD
aiobfd-0.2.dist-info/WHEEL
aiobfd-0.2.dist-info/entry_points.txt
aiobfd-0.2.dist-info/metadata.json
aiobfd-0.2.dist-info/top_level.txt
