Metadata-Version: 2.0
Name: aiobfd
Version: 0.2
Summary: Asynchronous BFD Daemon
Home-page: https://github.com/netedgeplus/aiobfd
Author: Kris Lambrechts
Author-email: kris@netedge.plus
License: MIT
Keywords: BFD Bidirectional Forwarding Detection rfc5880
Platform: UNKNOWN
Classifier: Development Status :: 3 - Alpha
Classifier: Framework :: AsyncIO
Classifier: Intended Audience :: Telecommunications Industry
Classifier: Topic :: System :: Networking :: Monitoring :: Hardware Watchdog
Classifier: License :: OSI Approved :: MIT License
Classifier: Programming Language :: Python :: 3 :: Only
Classifier: Programming Language :: Python :: 3.5
Classifier: Programming Language :: Python :: 3.6
Requires-Dist: bitstring
